[
  {
    "name": "永珍",
    "name_en": "Vientiane",
    "lat": 17.961,
    "lon": 102.61,
    "country": "寮國",
    "region": "亞洲",
    "quote": "就是我其实对永真的印象非常好",
    "context": "主持人摔壞手機後停留的城市，意外充滿悠哉與文青氛圍"
  },
  {
    "name": "旺陽",
    "name_en": "Vang Vieng",
    "lat": 18.924,
    "lon": 102.449,
    "country": "寮國",
    "region": "亞洲",
    "quote": "因为旺阳真的是一个party city",
    "context": "充滿歐美與韓國遊客派對氛圍及自然美景的城鎮"
  },
  {
    "name": "布魯拉棍",
    "name_en": "Blue Lagoon",
    "lat": 18.926,
    "lon": 102.395,
    "country": "寮國",
    "region": "亞洲",
    "quote": "很受欢迎的一个活动叫做布鲁拉棍",
    "context": "旺陽著名的跳水景點，有分不同編號"
  },
  {
    "name": "龍坡邦",
    "name_en": "Luang Prabang",
    "lat": 19.883,
    "lon": 102.133,
    "country": "寮國",
    "region": "亞洲",
    "quote": "因为龙坡邦我有去啊",
    "context": "寮國觀光能見度最高的世界遺產城鎮"
  },
  {
    "name": "豐沙灣",
    "name_en": "Phonsavan",
    "lat": 19.461,
    "lon": 103.181,
    "country": "寮國",
    "region": "亞洲",
    "quote": "就是封沙湾",
    "context": "主持人查錯地圖而意外前往的城鎮"
  },
  {
    "name": "豐沙里",
    "name_en": "Phongsaly",
    "lat": 21.683,
    "lon": 102.1,
    "country": "寮國",
    "region": "亞洲",
    "quote": "其实应该是我本来是要去封沙里",
    "context": "原本計畫前往觀賞少數民族阿卡村的地方"
  }
]