[
  {
    "name": "喀布爾國際機場",
    "name_en": "Kabul International Airport",
    "lat": 34.565,
    "lon": 69.212,
    "country": "阿富汗",
    "region": "亞洲",
    "quote": "很多阿富汗的男人在機場的跑道上追了那台飛機",
    "context": "提及2021年美軍撤退時的混亂畫面"
  },
  {
    "name": "阿富汗駐巴基斯坦大使館",
    "name_en": "Embassy of Afghanistan, Islamabad",
    "lat": 33.721,
    "lon": 73.111,
    "country": "巴基斯坦",
    "region": "亞洲",
    "quote": "他們首都在那邊有大使館，阿富汗大使館",
    "context": "辦理阿富汗入境簽證的地點"
  },
  {
    "name": "藍色清真寺",
    "name_en": "Blue Mosque (Shrine of Hazrat Ali)",
    "lat": 36.708,
    "lon": 67.11,
    "country": "阿富汗",
    "region": "亞洲",
    "quote": "那邊有一個藍色清真寺，這個藍色清真寺其實就是很漂亮，全部都是用藍色馬賽克",
    "context": "阿富汗行程的第一站，目前女性被禁止進入"
  },
  {
    "name": "巴米洋大佛",
    "name_en": "Buddhas of Bamiyan",
    "lat": 34.832,
    "lon": 67.823,
    "country": "阿富汗",
    "region": "亞洲",
    "quote": "他拿RPG火箭筒直接對著那個大佛發射，然後把他炸了一個稀巴爛",
    "context": "討論塔利班過去炸毀世界文化遺產的歷史"
  }
]