[
  {
    "name": "太平洋屋脊步道",
    "name_en": "Pacific Crest Trail",
    "lat": 42.0,
    "lon": -122.0,
    "country": "美國",
    "region": "美洲",
    "quote": "那條是路上不會有住宿，不會有餐廳，自己想辦法，完全是野外求生的概念",
    "context": "啟發來賓踏上徒步旅行的電影背景路線"
  },
  {
    "name": "聖雅各之路",
    "name_en": "Camino de Santiago",
    "lat": 42.88,
    "lon": -8.544,
    "country": "西班牙",
    "region": "歐洲",
    "quote": "有一條路叫做朝聖之路，然後她就是大家也是一直走路一直走路",
    "context": "來賓失戀後踏上的第一條長程徒步路線"
  },
  {
    "name": "葡萄牙之路",
    "name_en": "Camino Portugués",
    "lat": 41.15,
    "lon": -8.61,
    "country": "葡萄牙",
    "region": "歐洲",
    "quote": "我接著去走葡萄牙之路，葡萄牙之路大概240，等於是前前後後我走了1000多公里",
    "context": "來賓接續西班牙之路後所走的路線"
  },
  {
    "name": "英國之路",
    "name_en": "Camino Inglés",
    "lat": 43.362,
    "lon": -8.411,
    "country": "西班牙",
    "region": "歐洲",
    "quote": "去年九月又去走另外一條，就是英國之路，它是從西班牙北邊的一個港口開始",
    "context": "古代英國朝聖者渡海後登陸的朝聖路線"
  },
  {
    "name": "熊野古道",
    "name_en": "Kumano Kodo",
    "lat": 33.84,
    "lon": 135.773,
    "country": "日本",
    "region": "亞洲",
    "quote": "它叫做熊野古道，它是跟這個聖雅各之路算是姐妹道，他們是世界遺產為二兩條以參拜路",
    "context": "日本唯一與聖雅各之路締結姐妹道的遺產"
  },
  {
    "name": "四國遍路",
    "name_en": "Shikoku Henro",
    "lat": 34.0,
    "lon": 134.0,
    "country": "日本",
    "region": "亞洲",
    "quote": "還有一條路叫做四國遍路，比較有名的也叫朝聖之路",
    "context": "常與熊野古道被混淆的日本著名朝聖路"
  },
  {
    "name": "瀧尻王子",
    "name_en": "Takijiri-oji",
    "lat": 33.771,
    "lon": 135.59,
    "country": "日本",
    "region": "亞洲",
    "quote": "從一個叫做龍寒王子的地方，走到雄野本宮大社，38公里",
    "context": "熊野古道中邊路的起點（逐字稿誤記為龍寒）"
  },
  {
    "name": "熊野本宮大社",
    "name_en": "Kumano Hongu Taisha",
    "lat": 33.84,
    "lon": 135.773,
    "country": "日本",
    "region": "亞洲",
    "quote": "三天走到本宮大社終點，你就可以去領這個雙朝聖證書",
    "context": "熊野朝聖的核心終點，可領取雙朝聖證書"
  },
  {
    "name": "熊野那智大社",
    "name_en": "Kumano Nachi Taisha",
    "lat": 33.668,
    "lon": 135.89,
    "country": "日本",
    "region": "亞洲",
    "quote": "從另外一個神社叫做納志大社，納志大社到本宮大社，也是終點",
    "context": "熊野三山之一，此路段坡度極陡且艱辛"
  },
  {
    "name": "發心門王子",
    "name_en": "Hosshimon-oji",
    "lat": 33.854,
    "lon": 135.732,
    "country": "日本",
    "region": "亞洲",
    "quote": "從發西門王子走到本宮大社，7公里，它是最裡面算是最簡單的一段",
    "context": "熊野古道中最短且最輕鬆的朝聖路段"
  },
  {
    "name": "熊野速玉大社",
    "name_en": "Kumano Hayatama Taisha",
    "lat": 33.731,
    "lon": 135.984,
    "country": "日本",
    "region": "亞洲",
    "quote": "你要去參拜另外兩間神社，叫做納智大社跟樹玉大社",
    "context": "熊野三山之一（逐字稿誤記為樹玉大社）"
  },
  {
    "name": "高野山",
    "name_en": "Mount Koya",
    "lat": 34.214,
    "lon": 135.584,
    "country": "日本",
    "region": "亞洲",
    "quote": "從高野山走到本宮大社，這一條70公里，那一條路不好走",
    "context": "熊野古道小邊路的起點，難度極高的路段"
  },
  {
    "name": "中邊路",
    "name_en": "Nakahechi",
    "lat": 33.82,
    "lon": 135.65,
    "country": "日本",
    "region": "亞洲",
    "quote": "我現在在中邊路的第64號中間，南下第32公里處",
    "context": "熊野古道最主要的朝聖路徑名稱"
  }
]